amiyalog/__init__.py
amiyalog/handlers.py
amiyalog/manager.py
amiyalog/progress.py
amiyalog-0.0.3.dist-info/LICENSE
amiyalog-0.0.3.dist-info/METADATA
amiyalog-0.0.3.dist-info/WHEEL
amiyalog-0.0.3.dist-info/top_level.txt
amiyalog-0.0.3.dist-info/RECORD
