Metadata-Version: 2.1
Name: amiyalog
Version: 0.0.3
Summary: AmiyaBot 日志模块
Home-page: https://www.amiyabot.com/develop/advanced/logger.html
Author: vivien8261
Author-email: 826197021@qq.com
License: MIT Licence
Requires-Python: >=3.10
License-File: LICENSE
Requires-Dist: amiyautils~=0.0.2
Requires-Dist: concurrent-log-handler~=0.9.28
